CE222L_Project/verilog/output_reg.v
`timescale 1ns/1ps
module output_reg(
    input clk,
    input [7:0] data_in,
    input out_load,
    output reg [7:0] data_out
);
always @(posedge clk) begin
    if (out_load)
        data_out <= data_in;
end
endmodule

CE222L_Project/verilog/accumulator.v
`timescale 1ns/1ps  
module accumulator(  
    input clk,  
    input [7:0] data_in,  
    input acc_load,  
    output reg [7:0] acc_out,  
    output zero_flag  
);  

// Initialize to prevent X values in simulation
initial begin
    acc_out = 8'h00;
end

assign zero_flag = (acc_out == 8'b0);  

always @(posedge clk) begin  
    if (acc_load) 
        acc_out <= data_in;  
end

endmodule

CE222L_Project/verilog/alu.v
`timescale 1ns/1ps  
module alu(  
    input [7:0] a,  
    input [7:0] b,  
    input [2:0] op,  
    output reg [7:0] result  
);  

always @(*) begin  
    case(op)  
        3'b000: result = a + b;    // ADD  
        3'b001: result = a - b;    // SUB  
        3'b010: result = a & b;    // AND  
        3'b011: result = a | b;    // OR  
        3'b100: result = a ^ b;    // XOR  
        default: result = a;       // Pass through  
    endcase  
end  

endmodule

CE222L_Project/verilog/b_reg.v
module b_reg(
    input clk,
    input [7:0] data_in,
    input b_load,
    output reg [7:0] data_out
);

initial data_out = 8'h00;

always @(posedge clk) begin
    if (b_load)
        data_out <= data_in;  // Load data when b_load=1
end
endmodule

CE222L_Project/verilog/control_unit.v
module control_unit(
    input clk,
    input reset,
    input [3:0] opcode,
    input zero_flag,
    output reg pc_inc,
    output reg pc_jmp,
    output reg mem_read,
    output reg acc_load,
    output reg b_load,
    output reg [2:0] alu_op,
    output reg out_load,
    output [1:0] state  // Expose current state for debugging
);

parameter FETCH = 2'b00, DECODE = 2'b01, EXECUTE = 2'b10;
reg [1:0] current_state, next_state;

// Sequential state transition
always @(posedge clk or posedge reset) begin
    if (reset) current_state <= FETCH;
    else current_state <= next_state;
end

// Combinational output and next state logic
always @(*) begin
    // Default values
    pc_inc = 1'b0;
    pc_jmp = 1'b0;
    mem_read = 1'b0;
    acc_load = 1'b0;
    b_load = 1'b0;
    alu_op = 3'b000;
    out_load = 1'b0;
    next_state = current_state;

    case(current_state)
        FETCH: begin
            mem_read = 1'b1;
            next_state = DECODE;
        end
        
        DECODE: begin
            next_state = EXECUTE;
        end
        
        EXECUTE: begin
            case(opcode)
                4'b0000: begin // LDA
                    mem_read = 1'b1;
                    acc_load = 1'b1;
                    pc_inc = 1'b1;
                end
                
                4'b0001: begin // ADD
                    mem_read = 1'b1;
                    b_load = 1'b1;
                    alu_op = 3'b000;
                    acc_load = 1'b1;
                    pc_inc = 1'b1;
                end
                
                4'b0010: begin // SUB
                    mem_read = 1'b1;
                    b_load = 1'b1;
                    alu_op = 3'b001;
                    acc_load = 1'b1;
                    pc_inc = 1'b1;
                end
                
                4'b0011: begin // AND
                    mem_read = 1'b1;
                    b_load = 1'b1;
                    alu_op = 3'b010;
                    acc_load = 1'b1;
                    pc_inc = 1'b1;
                end
                
                4'b0100: begin // OR
                    mem_read = 1'b1;
                    b_load = 1'b1;
                    alu_op = 3'b011;
                    acc_load = 1'b1;
                    pc_inc = 1'b1;
                end
                
                4'b0101: begin // XOR
                    mem_read = 1'b1;
                    b_load = 1'b1;
                    alu_op = 3'b100;
                    acc_load = 1'b1;
                    pc_inc = 1'b1;
                end
                
                4'b0110: begin // JMP
                    pc_jmp = 1'b1;
                    pc_inc = 1'b0;
                end
                
                4'b0111: begin // JZ
                    pc_jmp = zero_flag;
                    pc_inc = ~zero_flag;
                end
                
                4'b1110: begin // OUT
                    out_load = 1'b1;
                    pc_inc = 1'b1;
                end
                
                default: begin // HLT and others
                    // No operation
                end
            endcase
            next_state = FETCH;
        end
    endcase
end

// Expose current state
assign state = current_state;

endmodule

CE222L_Project/verilog/ins_reg.v
`timescale 1ns/1ps
module ins_reg(
    input clk,
    input [7:0] instr_in,
    input ir_load,
    output reg [3:0] opcode,  // Correct 4-bit width
    output reg [3:0] operand   // Correct 4-bit width
);

initial begin
    opcode = 4'b0;
    operand = 4'b0;
end

always @(posedge clk) begin
    if (ir_load) begin
        opcode <= instr_in[7:4];
        operand <= instr_in[3:0];
    end
end
endmodule

CE222L_Project/verilog/memory.v
`timescale 1ns/1ps  
module memory(  
    input clk,  
    input [3:0] addr,  
    input mem_read,  
    input mem_write,  
    input [7:0] data_in,  
    output reg [7:0] data_out  
);  

reg [7:0] mem [0:15]; // 16 x 8-bit memory  

// Initialize data_out to prevent X values
initial begin
    data_out = 8'h00;
end

always @(posedge clk) begin  
    if (mem_write) 
        mem[addr] <= data_in;
    if (mem_read) 
        data_out <= mem[addr];  
end  

initial begin  
    // Instructions  
    mem[0] = 8'b0000_1010; // LDA [0Ah]  
    mem[1] = 8'b0001_1011; // ADD [0Bh]  
    mem[2] = 8'b0010_1100; // SUB [0Ch]  
    mem[3] = 8'b0011_1101; // AND [0Dh]  
    mem[4] = 8'b0100_1110; // OR  [0Eh]  
    mem[5] = 8'b0101_1111; // XOR [0Fh]  
    mem[6] = 8'b0110_1000; // JMP [08h]  
    mem[7] = 8'b0111_0000; // JZ  [00h]  
    mem[8] = 8'b1110_0000; // OUT  
    mem[9] = 8'b1111_0000; // HLT  

    // Data - Use correct hex indices
    mem[10] = 8'h0A; // 0Ah = 10  
    mem[11] = 8'h05; // 0Bh = 5
    mem[12] = 8'h03; // 0Ch = 3
    mem[13] = 8'h0C; // 0Dh = 12
    mem[14] = 8'h03; // 0Eh = 3
    mem[15] = 8'h05; // 0Fh = 5
end
endmodule

CE222L_Project/verilog/mar.v
`timescale 1ns/1ps
module mar(
    input clk,
    input [3:0] addr_in,
    input mar_load,
    output reg [3:0] addr_out
);
always @(posedge clk) begin
    if (mar_load)
        addr_out <= addr_in;
end
endmodule

CE222L_Project/verilog/program_counter.v
`timescale 1ns/1ps  
module program_counter(  
    input clk,  
    input reset,  
    input [3:0] jmp_addr,  
    input pc_inc,  
    input pc_jmp,  
    output reg [3:0] pc_out  
);  

always @(posedge clk or posedge reset) begin  
    if (reset) pc_out <= 4'b0;  
    else if (pc_jmp) pc_out <= jmp_addr;  
    else if (pc_inc) pc_out <= pc_out + 1;  
end  

endmodule

CE222L_Project/verilog/sap1_tb.v
`timescale 1ns/1ps
module sap1_tb;

// Clock and Reset
reg clk;
reg reset;

// Wires for interconnections
wire [3:0] pc_out;
wire [3:0] mar_out;
wire [7:0] mem_data_out;
wire [3:0] ir_opcode;
wire [3:0] ir_operand;
wire [7:0] acc_out;
wire [7:0] b_reg_out;
wire [7:0] alu_result;
wire [7:0] out_reg;
wire zero_flag;
wire [1:0] control_state;
wire [3:0] mar_addr_in = (control_state == 2'b00) ? pc_out : {4'b0, ir_operand};

// Control signals
wire pc_inc, pc_jmp, mem_read, acc_load, out_load, b_load;
wire [2:0] alu_op;

// Instantiate all modules with explicit connections
program_counter pc(
    .clk(clk),
    .reset(reset),
    .jmp_addr({4'b0, ir_operand}),
    .pc_inc(pc_inc),
    .pc_jmp(pc_jmp),
    .pc_out(pc_out)
);

mar mar_inst(
    .clk(clk),
    .addr_in(mar_addr_in),
    .mar_load(mem_read),
    .addr_out(mar_out)
);

memory mem(
    .clk(clk),
    .addr(mar_out[3:0]),
    .mem_read(mem_read),
    .mem_write(1'b0),
    .data_in(8'b0),
    .data_out(mem_data_out)
);

ins_reg ir(
    .clk(clk),
    .instr_in(mem_data_out),
    .ir_load(mem_read),
    .opcode(ir_opcode),
    .operand(ir_operand)
);

control_unit control(
    .clk(clk),
    .reset(reset),
    .opcode(ir_opcode),
    .zero_flag(zero_flag),
    .pc_inc(pc_inc),
    .pc_jmp(pc_jmp),
    .mem_read(mem_read),
    .acc_load(acc_load),
    .b_load(b_load),
    .alu_op(alu_op),
    .out_load(out_load),
    .state(control_state)
);

b_reg b_register(
    .clk(clk),
    .data_in(mem_data_out),
    .b_load(b_load),
    .data_out(b_reg_out)
);

alu alu_inst(
    .a(acc_out),
    .b(b_reg_out),
    .op(alu_op),
    .result(alu_result)
);

accumulator acc(
    .clk(clk),
    .data_in(alu_result),
    .acc_load(acc_load),
    .acc_out(acc_out),
    .zero_flag(zero_flag)
);

output_reg out_reg_inst(
    .clk(clk),
    .data_in(acc_out),
    .out_load(out_load),
    .data_out(out_reg)
);

// Clock generation
initial begin
    clk = 0;
    forever #5 clk = ~clk;
end

// Main test sequence
initial begin
    $dumpfile("sap1_wave.vcd");
    $dumpvars(0, sap1_tb);
    
    // Initialize signals
    reset = 1;
    #20 reset = 0;
    
    $display("Starting SAP-1 Simulation");
    
    // Run simulation for sufficient time
    #400 $finish;
end

endmodule

CE222L_Project/verilog/sap1_wave.vcd
$date
	Mon May 05 18:30:08 2025
$end
$version
	Icarus Verilog
$end
$timescale
	1ps
$end
$scope module sap1_tb $end
$var wire 1 ! zero_flag $end
$var wire 4 " pc_out [3:0] $end
$var wire 1 # pc_jmp $end
$var wire 1 $ pc_inc $end
$var wire 8 % out_reg [7:0] $end
$var wire 1 & out_load $end
$var wire 1 ' mem_read $end
$var wire 8 ( mem_data_out [7:0] $end
$var wire 4 ) mar_out [3:0] $end
$var wire 4 * mar_addr_in [3:0] $end
$var wire 4 + ir_operand [3:0] $end
$var wire 4 , ir_opcode [3:0] $end
$var wire 2 - control_state [1:0] $end
$var wire 8 . b_reg_out [7:0] $end
$var wire 1 / b_load $end
$var wire 8 0 alu_result [7:0] $end
$var wire 3 1 alu_op [2:0] $end
$var wire 8 2 acc_out [7:0] $end
$var wire 1 3 acc_load $end
$var reg 1 4 clk $end
$var reg 1 5 reset $end
$scope module acc $end
$var wire 1 4 clk $end
$var wire 1 ! zero_flag $end
$var wire 8 6 data_in [7:0] $end
$var wire 1 3 acc_load $end
$var reg 8 7 acc_out [7:0] $end
$upscope $end
$scope module alu_inst $end
$var wire 8 8 a [7:0] $end
$var wire 3 9 op [2:0] $end
$var wire 8 : b [7:0] $end
$var reg 8 ; result [7:0] $end
$upscope $end
$scope module b_register $end
$var wire 1 4 clk $end
$var wire 8 < data_in [7:0] $end
$var wire 1 / b_load $end
$var reg 8 = data_out [7:0] $end
$upscope $end
$scope module control $end
$var wire 1 4 clk $end
$var wire 1 5 reset $end
$var wire 2 > state [1:0] $end
$var wire 1 ! zero_flag $end
$var wire 4 ? opcode [3:0] $end
$var parameter 2 @ DECODE $end
$var parameter 2 A EXECUTE $end
$var parameter 2 B FETCH $end
$var reg 1 3 acc_load $end
$var reg 3 C alu_op [2:0] $end
$var reg 1 / b_load $end
$var reg 2 D current_state [1:0] $end
$var reg 1 ' mem_read $end
$var reg 2 E next_state [1:0] $end
$var reg 1 & out_load $end
$var reg 1 $ pc_inc $end
$var reg 1 # pc_jmp $end
$upscope $end
$scope module ir $end
$var wire 1 4 clk $end
$var wire 1 ' ir_load $end
$var wire 8 F instr_in [7:0] $end
$var reg 4 G opcode [3:0] $end
$var reg 4 H operand [3:0] $end
$upscope $end
$scope module mar_inst $end
$var wire 4 I addr_in [3:0] $end
$var wire 1 4 clk $end
$var wire 1 ' mar_load $end
$var reg 4 J addr_out [3:0] $end
$upscope $end
$scope module mem $end
$var wire 4 K addr [3:0] $end
$var wire 1 4 clk $end
$var wire 8 L data_in [7:0] $end
$var wire 1 ' mem_read $end
$var wire 1 M mem_write $end
$var reg 8 N data_out [7:0] $end
$upscope $end
$scope module out_reg_inst $end
$var wire 1 4 clk $end
$var wire 8 O data_in [7:0] $end
$var wire 1 & out_load $end
$var reg 8 P data_out [7:0] $end
$upscope $end
$scope module pc $end
$var wire 1 4 clk $end
$var wire 4 Q jmp_addr [3:0] $end
$var wire 1 $ pc_inc $end
$var wire 1 # pc_jmp $end
$var wire 1 5 reset $end
$var reg 4 R pc_out [3:0] $end
$upscope $end
$upscope $end
$enddefinitions $end
$comment Show the parameter values. $end
$dumpall
b0 B
b10 A
b1 @
$end
#0
$dumpvars
b0 R
b0 Q
bx P
b0 O
b0 N
0M
b0 L
bx K
bx J
b0 I
b0 H
b0 G
b0 F
b1 E
b0 D
b0 C
b0 ?
b0 >
b0 =
b0 <
b0 ;
b0 :
b0 9
b0 8
b0 7
b0 6
15
04
03
b0 2
b0 1
b0 0
0/
b0 .
b0 -
b0 ,
b0 +
b0 *
bx )
b0 (
1'
0&
bx %
0$
0#
b0 "
1!
$end
#5000
b0 )
b0 J
b0 K
bx (
bx <
bx F
bx N
14
#10000
04
#15000
bx Q
b1 E
1'
bx +
bx H
bx ,
bx ?
bx G
b1010 (
b1010 <
b1010 F
b1010 N
14
#20000
04
05
#25000
b1010 *
b1010 I
b1010 Q
b10 E
0'
b1010 +
b1010 H
b0 ,
b0 ?
b0 G
b1 -
b1 >
b1 D
14
#30000
04
#35000
b0 E
1$
13
1'
b10 -
b10 >
b10 D
14
#40000
04
#45000
b1 *
b1 I
b1 E
03
1'
0$
b1010 )
b1010 J
b1010 K
b0 -
b0 >
b0 D
b1 "
b1 R
14
#50000
04
#55000
b1010 *
b1010 I
b10 E
0'
b1 )
b1 J
b1 K
b1 -
b1 >
b1 D
14
#60000
04
#65000
b0 E
1$
13
1'
b10 -
b10 >
b10 D
14
#70000
04
#75000
b10 *
b10 I
b1 E
03
1'
0$
b11011 (
b11011 <
b11011 F
b11011 N
b1010 )
b1010 J
b1010 K
b10 "
b10 R
b0 -
b0 >
b0 D
14
#80000
04
#85000
b1011 *
b1011 I
b1011 Q
b10 E
0'
b10 )
b10 J
b10 K
b1010 (
b1010 <
b1010 F
b1010 N
b1011 +
b1011 H
b1 ,
b1 ?
b1 G
b1 -
b1 >
b1 D
14
#90000
04
#95000
b0 E
1$
13
1/
1'
b10 -
b10 >
b10 D
14
#100000
04
#105000
b11 *
b11 I
b1010 Q
b1010 0
b1010 6
b1010 ;
b1 E
0/
03
1'
0$
b1011 )
b1011 J
b1011 K
b101100 (
b101100 <
b101100 F
b101100 N
b1010 +
b1010 H
b0 ,
b0 ?
b0 G
b1010 .
b1010 :
b1010 =
b0 -
b0 >
b0 D
b11 "
b11 R
14
#110000
04
#115000
b1100 *
b1100 I
b1100 Q
b10 E
0'
b1100 +
b1100 H
b10 ,
b10 ?
b10 G
b101 (
b101 <
b101 F
b101 N
b11 )
b11 J
b11 K
b1 -
b1 >
b1 D
14
#120000
04
#125000
b11110110 0
b11110110 6
b11110110 ;
b0 E
1$
13
b1 1
b1 9
b1 C
1/
1'
b10 -
b10 >
b10 D
14
#130000
04
#135000
b100 *
b100 I
b11111011 0
b11111011 6
b11111011 ;
b101 Q
b1 E
b0 1
b0 9
b0 C
0/
03
1'
0$
0!
b11110110 2
b11110110 7
b11110110 8
b11110110 O
b101 .
b101 :
b101 =
b101 +
b101 H
b0 ,
b0 ?
b0 G
b111101 (
b111101 <
b111101 F
b111101 N
b1100 )
b1100 J
b1100 K
b100 "
b100 R
b0 -
b0 >
b0 D
14
#140000
04
#145000
b1101 *
b1101 I
b1101 Q
b10 E
0'
b100 )
b100 J
b100 K
b11 (
b11 <
b11 F
b11 N
b1101 +
b1101 H
b11 ,
b11 ?
b11 G
b1 -
b1 >
b1 D
14
#150000
04
#155000
b100 0
b100 6
b100 ;
b0 E
1$
13
b10 1
b10 9
b10 C
1/
1'
b10 -
b10 >
b10 D
14
#160000
04
#165000
b101 *
b101 I
b11 Q
b111 0
b111 6
b111 ;
b1 E
b0 1
b0 9
b0 C
0/
03
1'
0$
b1101 )
b1101 J
b1101 K
b1001110 (
b1001110 <
b1001110 F
b1001110 N
b11 +
b11 H
b0 ,
b0 ?
b0 G
b11 .
b11 :
b11 =
b100 2
b100 7
b100 8
b100 O
b0 -
b0 >
b0 D
b101 "
b101 R
14
#170000
04
#175000
b1110 *
b1110 I
b1110 Q
b10 E
0'
b1110 +
b1110 H
b100 ,
b100 ?
b100 G
b1100 (
b1100 <
b1100 F
b1100 N
b101 )
b101 J
b101 K
b1 -
b1 >
b1 D
14
#180000
04
#185000
b0 E
1$
13
b11 1
b11 9
b11 C
1/
1'
b10 -
b10 >
b10 D
14
#190000
04
#195000
b110 *
b110 I
b10011 0
b10011 6
b10011 ;
b1100 Q
b1 E
b0 1
b0 9
b0 C
0/
03
1'
0$
b111 2
b111 7
b111 8
b111 O
b1100 .
b1100 :
b1100 =
b1100 +
b1100 H
b0 ,
b0 ?
b0 G
b1011111 (
b1011111 <
b1011111 F
b1011111 N
b1110 )
b1110 J
b1110 K
b110 "
b110 R
b0 -
b0 >
b0 D
14
#200000
04
#205000
b1111 *
b1111 I
b1111 Q
b10 E
0'
b110 )
b110 J
b110 K
b11 (
b11 <
b11 F
b11 N
b1111 +
b1111 H
b101 ,
b101 ?
b101 G
b1 -
b1 >
b1 D
14
#210000
04
#215000
b1011 0
b1011 6
b1011 ;
b0 E
1$
13
b100 1
b100 9
b100 C
1/
1'
b10 -
b10 >
b10 D
14
#220000
04
#225000
b111 *
b111 I
b11 Q
b1110 0
b1110 6
b1110 ;
b1 E
b0 1
b0 9
b0 C
0/
03
1'
0$
b1111 )
b1111 J
b1111 K
b1101000 (
b1101000 <
b1101000 F
b1101000 N
b11 +
b11 H
b0 ,
b0 ?
b0 G
b11 .
b11 :
b11 =
b1011 2
b1011 7
b1011 8
b1011 O
b0 -
b0 >
b0 D
b111 "
b111 R
14
#230000
04
#235000
b1000 *
b1000 I
b1000 Q
b10 E
0'
b1000 +
b1000 H
b110 ,
b110 ?
b110 G
b101 (
b101 <
b101 F
b101 N
b111 )
b111 J
b111 K
b1 -
b1 >
b1 D
14
#240000
04
#245000
b0 E
1#
b10 -
b10 >
b10 D
14
#250000
04
#255000
b1 E
1'
0#
b1000 "
b1000 R
b0 -
b0 >
b0 D
14
#260000
04
#265000
b101 *
b101 I
b101 Q
b10 E
0'
b1000 )
b1000 J
b1000 K
b1110000 (
b1110000 <
b1110000 F
b1110000 N
b101 +
b101 H
b0 ,
b0 ?
b0 G
b1 -
b1 >
b1 D
14
#270000
04
#275000
b0 E
1$
13
1'
b10 -
b10 >
b10 D
14
#280000
04
#285000
b1001 *
b1001 I
b0 Q
b10001 0
b10001 6
b10001 ;
b1 E
03
1'
0$
b101 )
b101 J
b101 K
b11100000 (
b11100000 <
b11100000 F
b11100000 N
b0 +
b0 H
b111 ,
b111 ?
b111 G
b1110 2
b1110 7
b1110 8
b1110 O
b0 -
b0 >
b0 D
b1001 "
b1001 R
14
#290000
04
#295000
b0 *
b0 I
b10 E
0'
b1110 ,
b1110 ?
b1110 G
b1011111 (
b1011111 <
b1011111 F
b1011111 N
b1001 )
b1001 J
b1001 K
b1 -
b1 >
b1 D
14
#300000
04
#305000
b0 E
1$
1&
b10 -
b10 >
b10 D
14
#310000
04
#315000
b1010 *
b1010 I
b1 E
1'
0&
0$
b1110 %
b1110 P
b1010 "
b1010 R
b0 -
b0 >
b0 D
14
#320000
04
#325000
b1111 *
b1111 I
b1111 Q
b10 E
0'
b1010 )
b1010 J
b1010 K
b11110000 (
b11110000 <
b11110000 F
b11110000 N
b1111 +
b1111 H
b101 ,
b101 ?
b101 G
b1 -
b1 >
b1 D
14
#330000
04
#335000
b1101 0
b1101 6
b1101 ;
b0 E
1$
13
b100 1
b100 9
b100 C
1/
1'
b10 -
b10 >
b10 D
14
#340000
04
#345000
b1011 *
b1011 I
b0 Q
b11111101 0
b11111101 6
b11111101 ;
b1 E
b0 1
b0 9
b0 C
0/
03
1'
0$
b1111 )
b1111 J
b1111 K
b1010 (
b1010 <
b1010 F
b1010 N
b0 +
b0 H
b1111 ,
b1111 ?
b1111 G
b11110000 .
b11110000 :
b11110000 =
b1101 2
b1101 7
b1101 8
b1101 O
b0 -
b0 >
b0 D
b1011 "
b1011 R
14
#350000
04
#355000
b1010 *
b1010 I
b1010 Q
b10 E
0'
b1010 +
b1010 H
b0 ,
b0 ?
b0 G
b101 (
b101 <
b101 F
b101 N
b1011 )
b1011 J
b1011 K
b1 -
b1 >
b1 D
14
#360000
04
#365000
b0 E
1$
13
1'
b10 -
b10 >
b10 D
14
#370000
04
#375000
b1100 *
b1100 I
b11101101 0
b11101101 6
b11101101 ;
b101 Q
b1 E
03
1'
0$
b11111101 2
b11111101 7
b11111101 8
b11111101 O
b101 +
b101 H
b1010 )
b1010 J
b1010 K
b1100 "
b1100 R
b0 -
b0 >
b0 D
14
#380000
04
#385000
b101 *
b101 I
b10 E
0'
b1100 )
b1100 J
b1100 K
b1010 (
b1010 <
b1010 F
b1010 N
b1 -
b1 >
b1 D
14
#390000
04
#395000
b0 E
1$
13
1'
b10 -
b10 >
b10 D
14
#400000
04
#405000
b1101 *
b1101 I
b1010 Q
b11011101 0
b11011101 6
b11011101 ;
b1 E
03
1'
0$
b101 )
b101 J
b101 K
b11 (
b11 <
b11 F
b11 N
b1010 +
b1010 H
b11101101 2
b11101101 7
b11101101 8
b11101101 O
b0 -
b0 >
b0 D
b1101 "
b1101 R
14
#410000
04
#415000
b11 *
b11 I
b11 Q
b10 E
0'
b11 +
b11 H
b1011111 (
b1011111 <
b1011111 F
b1011111 N
b1101 )
b1101 J
b1101 K
b1 -
b1 >
b1 D
14
